README.rst
setup.py
src/bitbangio.py
src/board.py
src/busio.py
src/digitalio.py
src/Adafruit_Micropython_Blinka.egg-info/PKG-INFO
src/Adafruit_Micropython_Blinka.egg-info/SOURCES.txt
src/Adafruit_Micropython_Blinka.egg-info/dependency_links.txt
src/Adafruit_Micropython_Blinka.egg-info/top_level.txt
src/adafruit_blinka/__init__.py
src/adafruit_blinka/agnostic/__init__.py
src/adafruit_blinka/agnostic/time.py
src/adafruit_blinka/board/__init__.py
src/adafruit_blinka/board/feather_huzzah.py
src/adafruit_blinka/board/nodemcu.py
src/adafruit_blinka/board/pyboard.py
src/adafruit_blinka/microcontroller/__init__.py
src/adafruit_blinka/microcontroller/esp8266/__init__.py
src/adafruit_blinka/microcontroller/esp8266/pin.py
src/adafruit_blinka/microcontroller/stm32/__init__.py
src/adafruit_blinka/microcontroller/stm32/pin.py
src/microcontroller/__init__.py
src/microcontroller/pin.py