Metadata-Version: 1.2
Name: Adafruit-Micropython-Blinka
Version: 1.0.0
Summary: A selection of packages for mirroring the CircuitPython API on hosts running micropython.
Home-page: https://github.com/adafruit/Adafruit_Micropython_Blinka
Author: Adafruit Industries
Author-email: python@adafruit.com
License: MIT
Platform: UNKNOWN
Classifier: License :: OSI Approved :: MIT License
Classifier: Programming Language :: Python
Classifier: Programming Language :: Python :: 3
Classifier: Programming Language :: Python :: 3.6
Classifier: Programming Language :: Python :: Implementation :: MicroPython
Requires-Python: >=3.6.0
